pyqint/spherical_harmonics.py
pyqint/cgf.py
pyqint/gto.py
pyqint/blender_render_molecule.py
pyqint/foster_boys.py
pyqint/geometry_optimization.py
pyqint/molecule.py
pyqint/_version.py
pyqint/pyqint_core.cpython-39-darwin.so
pyqint/__init__.py
pyqint/matrix_plotter.py
pyqint/element.py
pyqint/molecule_builder.py
pyqint/population_analysis.py
pyqint/blenderrender.py
pyqint/contour.py
pyqint/hf.py
pyqint/isosurface.py
pyqint/molecules/benzene.xyz
pyqint/molecules/ch4.xyz
pyqint/molecules/chlorobenzene.xyz
pyqint/molecules/ethylene.xyz
pyqint/molecules/co.xyz
pyqint/molecules/borane.xyz
pyqint/molecules/tetrahedrane.xyz
pyqint/molecules/h2o.xyz
pyqint/molecules/adenine.xyz
pyqint/molecules/co2.xyz
pyqint/molecules/caffeine.xyz
pyqint/molecules/lih.xyz
pyqint/molecules/buckminsterfullerence.xyz
pyqint/molecules/nh3.xyz
pyqint/molecules/dodecahedrane.xyz
pyqint/molecules/h2.xyz
pyqint/molecules/he.xyz
pyqint/molecules/annulene.xyz
pyqint/molecules/bf3.xyz
pyqint/molecules/trans-1-3-butadiene.xyz
pyqint/molecules/acetylene.xyz
pyqint/molecules/n2.xyz
pyqint/molecules/o2.xyz
pyqint/molecules/cubane.xyz
pyqint/molecules/ethanol.xyz
pyqint/basissets/p631.json
pyqint/basissets/aug-cc-pVDZ.json
pyqint/basissets/aug-cc-pVQZ.json
pyqint/basissets/sto3g.json
pyqint/basissets/p321.json
pyqint/basissets/sto6g.json
pyqint/basissets/aug-cc-pVTZ.json
pyqint/blender/blender_render_molecule.py
pyqint-1.4.1.dist-info/RECORD
pyqint-1.4.1.dist-info/WHEEL
pyqint-1.4.1.dist-info/METADATA
