Metadata-Version: 2.1
Name: pyqint
Version: 1.4.1
Summary: Python package for evaluating integrals of Gaussian type orbitals
Author-Email: Ivo Filot <ivo@ivofilot.nl>
License: GPL-3.0-only
Project-URL: Homepage, https://github.com/ifilot/pyqint
Requires-Python: >=3.9
Requires-Dist: numpy
Requires-Dist: scipy
Requires-Dist: matplotlib
Requires-Dist: tqdm
